windb/__init__.py
windb/dbconn.py
windb/wsd.py
windb/wsi.py
windb-0.0.2.dist-info/DESCRIPTION.rst
windb-0.0.2.dist-info/METADATA
windb-0.0.2.dist-info/RECORD
windb-0.0.2.dist-info/WHEEL
windb-0.0.2.dist-info/metadata.json
windb-0.0.2.dist-info/top_level.txt
