Metadata-Version: 2.0
Name: windb
Version: 0.0.2
Summary: Wind + MongoDb
Home-page: https://github.com/fuchen/windb
Author: fuchen
Author-email: ink.pad@163.com
License: UNKNOWN
Platform: UNKNOWN
Requires-Dist: loguru
Requires-Dist: pdwind
Requires-Dist: pymongo
